import_here.py
import_here-0.3.dist-info/METADATA
import_here-0.3.dist-info/WHEEL
import_here-0.3.dist-info/entry_points.txt
import_here-0.3.dist-info/top_level.txt
import_here-0.3.dist-info/RECORD
