Metadata-Version: 2.1
Name: import-here
Version: 0.3
Summary: `import` module from same directory.
Home-page: https://github.com/weaming/import-here
Author: weaming
Author-email: garden.yuen@gmail.com
License: UNKNOWN
Project-URL: Source, https://github.com/weaming/import-here
Project-URL: Bug Reports, https://github.com/weaming/import-here
Keywords: math
Platform: UNKNOWN
